CHANGES.rst
MAINTAINERS.txt
MANIFEST.in
README.rst
buildout.cfg
setup.cfg
setup.py
src/__init__.py
src/erp5diff.1
src/ERP5Diff/ERP5Diff.py
src/ERP5Diff/__init__.py
src/erp5diff.egg-info/PKG-INFO
src/erp5diff.egg-info/SOURCES.txt
src/erp5diff.egg-info/dependency_links.txt
src/erp5diff.egg-info/entry_points.txt
src/erp5diff.egg-info/not-zip-safe
src/erp5diff.egg-info/requires.txt
src/erp5diff.egg-info/top_level.txt
src/interfaces/__init__.py
src/interfaces/erp5diff.py
src/tests/__init__.py
src/tests/test_erp5diff.py