Metadata-Version: 2.1
Name: erp5diff
Version: 0.8.1.9
Summary: XUpdate Generator for ERP5
Home-page: https://lab.nexedi.com/nexedi/erp5diff/
Author: Yoshinori OKUJI
Author-email: yo@nexedi.com
License: GPL
Classifier: License :: OSI Approved :: GNU General Public License (GPL)
Classifier: Operating System :: OS Independent
Classifier: Topic :: Text Processing :: Markup :: XML
Classifier: Topic :: Utilities
